cli_music_downloader/__init__.py
cli_music_downloader/batch_metadata.py
cli_music_downloader/cli.py
cli_music_downloader/download_music.py
cli_music_downloader/lyrics_metadata.py
cli_music_downloader/metadata_manager.py
cli_music_downloader-1.0.0.dist-info/licenses/LICENSE
cli_music_downloader-1.0.0.dist-info/METADATA
cli_music_downloader-1.0.0.dist-info/WHEEL
cli_music_downloader-1.0.0.dist-info/entry_points.txt
cli_music_downloader-1.0.0.dist-info/top_level.txt
cli_music_downloader-1.0.0.dist-info/RECORD
