Metadata-Version: 2.4
Name: CLI-Music-Downloader
Version: 1.0.0
Summary: A powerful command-line music downloader with automatic album artwork and intelligent organization
Author-email: Jordan Lang <jordolang@example.com>
Maintainer-email: Jordan Lang <jordolang@example.com>
License: MIT License
Project-URL: Homepage, https://github.com/jordolang/CLI-Music-Downloader
Project-URL: Repository, https://github.com/jordolang/CLI-Music-Downloader.git
Project-URL: Documentation, https://github.com/jordolang/CLI-Music-Downloader#readme
Project-URL: Bug Tracker, https://github.com/jordolang/CLI-Music-Downloader/issues
Project-URL: Changelog, https://github.com/jordolang/CLI-Music-Downloader/releases
Keywords: music,downloader,youtube,metadata,album-art,mp3,lyrics,cli,musicbrainz,shazam
Classifier: Development Status :: 4 - Beta
Classifier: Intended Audience :: End Users/Desktop
Classifier: License :: OSI Approved :: MIT License
Classifier: Operating System :: MacOS
Classifier: Operating System :: POSIX :: Linux
Classifier: Programming Language :: Python :: 3
Classifier: Programming Language :: Python :: 3.8
Classifier: Programming Language :: Python :: 3.9
Classifier: Programming Language :: Python :: 3.10
Classifier: Programming Language :: Python :: 3.11
Classifier: Programming Language :: Python :: 3.12
Classifier: Topic :: Multimedia :: Sound/Audio
Classifier: Topic :: Multimedia :: Sound/Audio :: Conversion
Classifier: Topic :: Internet :: WWW/HTTP
Classifier: Topic :: System :: Archiving
Classifier: Topic :: Utilities
Classifier: Environment :: Console
Requires-Python: >=3.8
License-File: LICENSE
Requires-Dist: instantmusic>=2.0
Requires-Dist: eyed3>=0.9.0
Requires-Dist: mutagen>=1.45.0
Requires-Dist: requests>=2.25.0
Requires-Dist: lyricsgenius>=3.0.0
Requires-Dist: shazamio>=0.3.0
Requires-Dist: musicbrainzngs>=0.7.0
Requires-Dist: pylast>=5.0.0
Requires-Dist: discogs-client>=2.0.0
Requires-Dist: aiohttp>=3.8.0
Requires-Dist: aiofiles>=0.8.0
Requires-Dist: Pillow>=8.0.0
Provides-Extra: dev
Requires-Dist: pytest>=6.0.0; extra == "dev"
Requires-Dist: pytest-asyncio>=0.21.0; extra == "dev"
Requires-Dist: pytest-mock>=3.10.0; extra == "dev"
Requires-Dist: pytest-cov>=4.0.0; extra == "dev"
Requires-Dist: black>=22.0.0; extra == "dev"
Requires-Dist: isort>=5.10.0; extra == "dev"
Requires-Dist: flake8>=4.0.0; extra == "dev"
Requires-Dist: mypy>=0.991; extra == "dev"
Requires-Dist: build>=0.8.0; extra == "dev"
Requires-Dist: twine>=4.0.0; extra == "dev"
Provides-Extra: docs
Requires-Dist: mkdocs>=1.4.0; extra == "docs"
Requires-Dist: mkdocs-material>=8.0.0; extra == "docs"
Requires-Dist: mkdocs-awesome-pages-plugin>=2.8.0; extra == "docs"
Provides-Extra: audio-fingerprinting
Requires-Dist: acrcloud>=1.4.0; extra == "audio-fingerprinting"
Provides-Extra: all
Requires-Dist: CLI-Music-Downloader[audio-fingerprinting,dev,docs]; extra == "all"
Dynamic: license-file
